kilmlogger/__init__.py
kilmlogger/config.py
kilmlogger/constants.py
kilmlogger/correlation.py
kilmlogger/envs.py
kilmlogger/handler.py
kilmlogger/processor.py
kilmlogger/styles.py
kilmlogger/utils.py
kilmlogger/services/scribe/client.py
kilmlogger/services/scribe/grpc/scribelog.proto
kilmlogger/services/scribe/grpc/scribelog_pb2.py
kilmlogger/services/scribe/grpc/scribelog_pb2.pyi
kilmlogger/services/scribe/grpc/scribelog_pb2_grpc.py
kilmlogger-0.2.3.dist-info/METADATA
kilmlogger-0.2.3.dist-info/WHEEL
kilmlogger-0.2.3.dist-info/RECORD
