Metadata-Version: 2.1
Name: kilmlogger
Version: 0.2.3
Summary: The Python Logger for all KiLM's Project
Project-URL: Documentation, https://github.com/unknown/kilmlogger#readme
Project-URL: Issues, https://github.com/unknown/kilmlogger/issues
Project-URL: Source, https://github.com/unknown/kilmlogger
Author-email: vietnh8 <vietnh8@vng.com.vn>
License-Expression: MIT
Classifier: Development Status :: 4 - Beta
Classifier: Programming Language :: Python
Classifier: Programming Language :: Python :: 3.11
Classifier: Programming Language :: Python :: 3.12
Classifier: Programming Language :: Python :: Implementation :: CPython
Classifier: Programming Language :: Python :: Implementation :: PyPy
Requires-Python: >=3.8
Requires-Dist: asgi-correlation-id<5.0.0,>=4.2.0
Requires-Dist: grpcio<2.0.0,>=1.60.0
Requires-Dist: protobuf<5.0.0,>=4.25.1
Requires-Dist: pydantic-settings<3.0.0,>=2.1.0
Requires-Dist: pydantic<3.0.0,>=2.5.3
Requires-Dist: starlette>=0.36.3
Requires-Dist: structlog<24.0.0,>=23.3.0
